qe_analyzer/__init__.py
qe_analyzer/convergenceTests.py
qe_analyzer/copyPaste.py
qe_analyzer/electronBands.py
qe_analyzer/phonons.py
qe_analyzer-0.0.7.dist-info/LICENSE
qe_analyzer-0.0.7.dist-info/METADATA
qe_analyzer-0.0.7.dist-info/WHEEL
qe_analyzer-0.0.7.dist-info/top_level.txt
qe_analyzer-0.0.7.dist-info/RECORD
