Metadata-Version: 2.1
Name: qe-analyzer
Version: 0.0.7
Summary: A small package for analyzing quantum espresso outputs
Home-page: https://github.com/euclidmenot2/qe_analyzer
Author: Elizabeth Pogue
Author-email: epogue1@jhu.edu
License: UNKNOWN
Platform: UNKNOWN
Classifier: Programming Language :: Python :: 3
Classifier: License :: OSI Approved :: MIT License
Classifier: Operating System :: OS Independent
Requires-Python: >=3.6
